my_chatbot/__init__.py
my_chatbot/app.py
my_chatbot/static/css/style.css
my_chatbot/static/js/script.js
my_chatbot/templates/index.html
my_chatbot_package-0.1.0.dist-info/METADATA
my_chatbot_package-0.1.0.dist-info/WHEEL
my_chatbot_package-0.1.0.dist-info/entry_points.txt
my_chatbot_package-0.1.0.dist-info/top_level.txt
my_chatbot_package-0.1.0.dist-info/RECORD
