Metadata-Version: 2.1
Name: my-chatbot-package
Version: 0.1.0
Summary: A chatbot package for library inquiries
Home-page: https://github.com/yourusername/my_chatbot_package
Author: Your Name
Author-email: your_email@example.com
Classifier: Programming Language :: Python :: 3
Classifier: License :: OSI Approved :: MIT License
Classifier: Operating System :: OS Independent
Requires-Dist: flask
Requires-Dist: mylibrary
